Metadata-Version: 1.0
Name: distributions-types
Version: 0.1
Summary: Gaussian and binomial distributions
Home-page: UNKNOWN
Author: Shubhangi Agrawal
Author-email: UNKNOWN
License: UNKNOWN
Platform: UNKNOWN
